[
    {
        "id": 0,
        "name": "To do",
        "tasks": [
            {
                "name": "Налить чай",
                "status": "srochno",
                "description": "Чай должен чёрный, превосходного отбора. К чаю предоставить закуски.",
                "time": "1"
            },
            {
                "name": "sdfsd",
                "status": "nesrochno",
                "description": "Lorem ipsum dolor sit amet, consectetur adipiscing elit, sed do eiusmod tempor incididunt ut labore et dolore magna aliqua. Aenean vel elit scelerisque mauris pellentesque.",
                "time": "1"
            }
        ]
    },
    {
        "id": 1,
        "name": "In work",
        "tasks": [
            {
                "name": "sdfsd",
                "status": "srochno",
                "time": "1"
            },
            {
                "name": "sdfsd",
                "status": "med",
                "time": "1"
            },
            {
                "name": "sdfsd",
                "status": "nesrochno",
                "time": "1"
            },
            {
                "name": "sdfsd",
                "status": "supernesrochno",
                "time": "1"
            }
        ]
    },
    {
        "id": 2,
        "name": "Done",
        "tasks": [
            {
                "name": "sdfsd",
                "status": "supernesrochno",
                "time": "1"
            },
            {
                "name": "sdfsd",
                "status": "supernesrochno",
                "time": "1"
            }
        ]
    },
    {
        "id": 1,
        "name": "In work",
        "tasks": [
            {
                "name": "sdfsd",
                "status": "srochno",
                "time": "1"
            },
            {
                "name": "sdfsd",
                "status": "med",
                "time": "1"
            },
            {
                "name": "sdfsd",
                "status": "nesrochno",
                "time": "1"
            },
            {
                "name": "sdfsd",
                "status": "supernesrochno",
                "time": "1"
            }
        ]
    },
    {
        "id": 1,
        "name": "In work",
        "tasks": [
            {
                "name": "sdfsd",
                "status": "srochno",
                "time": "1"
            },
            {
                "name": "sdfsd",
                "status": "med",
                "time": "1"
            },
            {
                "name": "sdfsd",
                "status": "nesrochno",
                "time": "1"
            },
            {
                "name": "sdfsd",
                "status": "supernesrochno",
                "time": "1"
            }
        ]
    }
]